T_BAG/T_BAG_main.py
T_BAG/__init__.py
T_BAG/__main__.py
T_BAG/beings.py
T_BAG/commands.py
T_BAG/event.py
T_BAG/items.py
T_BAG/rooms.py
T_BAG/utils.py
t_bag-1.1.3.dist-info/METADATA
t_bag-1.1.3.dist-info/WHEEL
t_bag-1.1.3.dist-info/entry_points.txt
t_bag-1.1.3.dist-info/top_level.txt
t_bag-1.1.3.dist-info/RECORD
